{
  "greeting": "Hello",
  "name": "from Seoul!",
  "greetingText1": "Every great product has a story,",
  "greetingText2": "and I'm here to help you tell yours.",
  "text1": "A website isn't just a collection of pages...",
  "text2": "I believe in understanding your brand's essence, its unique voice,",
  "text3": "and translating that into an intuitive and captivating digital journey.",
  "textInChatBox": "Templates and AI build sites. But do they build *your story*?",
  "sendButtonLabel": "Ask AI",
  "sendButtonLabelAlt": "Let's Talk",
  "text4": "Let's weave your vision into a compelling, interactive",
  "text4Adjective": "story",
  "text5ContentPart1": "Great design tells a compelling",
  "text5ContentPart2": "story",
  "smiley": ":)",
  "bigTextPart1": "S",
  "bigTextPart2": "TORY",
  "imagePath": "img/UXUI.png",
  "wishHeadingPart1": "Your Story",
  "wishHeadingPart2": "My Design!",
  "outroText": "Ready to begin your digital narrative?",
  "replayText": "Let’s create together!",
  "outroSmiley": ":)",
  "wishText": "Crafting narratives through design."
}